localsage/__init__.py
localsage/sage.py
localsage/sage_math_sanitizer.py
localsage-1.3.1.dist-info/licenses/LICENSE
tests/__init__.py
tests/test_sage_math_sanitizer.py
localsage-1.3.1.dist-info/METADATA
localsage-1.3.1.dist-info/WHEEL
localsage-1.3.1.dist-info/entry_points.txt
localsage-1.3.1.dist-info/top_level.txt
localsage-1.3.1.dist-info/RECORD
