Metadata-Version: 2.4
Name: localsage
Version: 1.3.1
Summary: A lightweight, elegant CLI for AI chat.
Author-email: Kyle Garcia <kylegarcia142@gmail.com>
Maintainer-email: Kyle Garcia <kylegarcia142@gmail.com>
License-Expression: MIT
Project-URL: Homepage, https://github.com/Kyleg142/localsage
Project-URL: Repository, https://github.com/Kyleg142/localsage
Project-URL: Issues, https://github.com/Kyleg142/localsage/issues
Keywords: ollama,llamacpp,openai,llm,ai,terminal,cli
Classifier: Programming Language :: Python :: 3
Classifier: Environment :: Console
Classifier: Intended Audience :: Developers
Classifier: Intended Audience :: End Users/Desktop
Classifier: Intended Audience :: Other Audience
Classifier: Operating System :: MacOS
Classifier: Operating System :: Microsoft :: Windows :: Windows 10
Classifier: Operating System :: Microsoft :: Windows :: Windows 11
Classifier: Operating System :: POSIX :: Linux
Classifier: Topic :: Terminals
Classifier: Topic :: Scientific/Engineering :: Artificial Intelligence
Requires-Python: >=3.10
License-File: LICENSE
Requires-Dist: rich>=14.2.0
Requires-Dist: tiktoken>=0.11.0
Requires-Dist: openai>=2.7.1
Requires-Dist: prompt_toolkit>=3.0.52
Requires-Dist: platformdirs>=4.5.0
Requires-Dist: keyring>=25.6.0
Requires-Dist: pylatexenc>=2.10
Dynamic: license-file
